csdn_visitors/CSDN.py
csdn_visitors/__init__.py
csdn_visitors-2.2.2.dist-info/LICENSE
csdn_visitors-2.2.2.dist-info/METADATA
csdn_visitors-2.2.2.dist-info/WHEEL
csdn_visitors-2.2.2.dist-info/top_level.txt
csdn_visitors-2.2.2.dist-info/RECORD
