Metadata-Version: 2.1
Name: csdn-visitors
Version: 2.2.2
Summary: Swipe CSDN visitors in batches
Home-page: https://github.com/Amiee-well/CSDN
Author: Lux
Author-email: 1223411083@qq.com
License: UNKNOWN
Platform: UNKNOWN
Classifier: Programming Language :: Python :: 3
Classifier: License :: OSI Approved :: MIT License
Classifier: Operating System :: OS Independent
Requires-Dist: requests
Requires-Dist: lxml
